src/__init__.py
src/idgenerator.py
src/utils.py
test/__init__.py
test/test_idgenerator.py
shanku_id_generator-0.0.10.dist-info/LICENSE
shanku_id_generator-0.0.10.dist-info/METADATA
shanku_id_generator-0.0.10.dist-info/WHEEL
shanku_id_generator-0.0.10.dist-info/top_level.txt
shanku_id_generator-0.0.10.dist-info/RECORD
